MANIFEST.in
README.md
requirements.txt
setup.py
GoogleScraper/__init__.py
GoogleScraper/__main__.py
GoogleScraper/async_mode.py
GoogleScraper/caching.py
GoogleScraper/commandline.py
GoogleScraper/config.py
GoogleScraper/core.py
GoogleScraper/database.py
GoogleScraper/http_mode.py
GoogleScraper/log.py
GoogleScraper/output_converter.py
GoogleScraper/parsing.py
GoogleScraper/proxies.py
GoogleScraper/scrape_config.py
GoogleScraper/scrape_jobs.py
GoogleScraper/scraping.py
GoogleScraper/search_engine_parameters.py
GoogleScraper/selenium_mode.py
GoogleScraper/socks.py
GoogleScraper/user_agents.py
GoogleScraper/utils.py
GoogleScraper/version.py
GoogleScraper.egg-info/PKG-INFO
GoogleScraper.egg-info/SOURCES.txt
GoogleScraper.egg-info/dependency_links.txt
GoogleScraper.egg-info/entry_points.txt
GoogleScraper.egg-info/requires.txt
GoogleScraper.egg-info/top_level.txt