Metadata-Version: 1.0
Name: GoogleScraper
Version: 0.2.0
Summary: A module to scrape and extract links, titles and descriptions from various search engines. Supports google,bing,yandex and many more.
Home-page: http://incolumitas.com
Author: Nikolai Tschacher
Author-email: admin@incolumitas.com
License: UNKNOWN
Platform: UNKNOWN
